tfpromote
