Metadata-Version: 1.1
Name: tfpromote
Version: 0.2.0
Summary: Compare and promote Terraform files from dev to prod environments.
Home-page: https://github.com/billtrust/terraform-promote
Author: Doug Kerwin
Author-email: dkerwin@billtrust.com
License: MIT
Keywords: terraform
Platform: UNKNOWN
Classifier: Intended Audience :: Developers
Classifier: Natural Language :: English
Classifier: License :: OSI Approved :: MIT License
Classifier: Programming Language :: Python
Classifier: Programming Language :: Python :: 3
Classifier: Programming Language :: Python :: 3.6
